{"items": [{"last_access_date": 1477649503, "user_id": 6236177, "last_modified_date": 1461248144, "profile_image": "https://lh4.googleusercontent.com/-jmT1N7J54dk/AAAAAAAAAAI/AAAAAAAAAGI/ezx9XibnJp4/photo.jpg?sz=128", "display_name": "Cedrik", "badge_counts": {"gold": 0, "silver": 0, "bronze": 2}, "link": "http://stackoverflow.com/users/6236177/cedrik", "reputation_change_year": 10, "reputation_change_quarter": 10, "reputation_change_day": 0, "is_employee": false, "account_id": 8295910, "website_url": "", "user_type": "registered", "reputation_change_month": 0, "reputation_change_week": 0, "creation_date": 1461248004, "reputation": 11}], "quota_max": 10000, "quota_remaining": 8117, "has_more": false}