{"items": [{"last_access_date": 1477934378, "user_id": 999284, "last_modified_date": 1463836329, "profile_image": "https://www.gravatar.com/avatar/94f94fc0d0e083d4542b5b75229842d9?s=128&d=identicon&r=PG", "display_name": "Mateus Brum", "badge_counts": {"gold": 0, "silver": 0, "bronze": 0}, "link": "http://stackoverflow.com/users/999284/mateus-brum", "reputation_change_year": 0, "reputation_change_quarter": 0, "reputation_change_day": 0, "is_employee": false, "account_id": 979057, "website_url": "", "user_type": "registered", "reputation_change_month": 0, "reputation_change_week": 0, "creation_date": 1318859548, "reputation": 1}], "quota_max": 10000, "quota_remaining": 8613, "has_more": false}